seminars/week06/debouncer/debouncer.v
module debouncer #(parameter WIDTH = 10, parameter PERIOD = 500)(
	input clk,
	input clken,
	input in,
	output reg out);

    reg [WIDTH - 1:0] counter;

    always @(posedge clk)
        if (clken)
            if (counter == PERIOD - 1)
            begin
                counter <= 0;
                out     <= in;
            end
            else
                counter <= counter + 1;
endmodule

seminars/week06/debouncer/debouncer_tb.v
`timescale 1ns/1ns

module debouncer_tb;
    parameter PERIOD     = 10;
    parameter TEST_COUNT = 20;

    integer i;

    reg clk;
    reg clken;
    reg in;
    reg error;

    // Standard 1364-2005:
    // start address for readmem is the left address of memory.
    // might be different in quartus
    reg [0:1] data[0:19];

    wire out;

    debouncer #(.WIDTH(2), .PERIOD(3)) db(.clk(clk), .clken(clken), .in(in), .out(out));

    initial begin
        clk         = 0;
        clken       = 1;
        in          = 0;
        error       = 0;

        db.counter  = 0;
        db.out      = 0;

        $readmemb("data.b", data);
    end

    initial
        forever #(PERIOD / 2.0)
            clk = ~clk;

    initial begin
        for (i = 0; i < 20; i += 1)
        begin
            @(posedge clk)
            in = data[i][0];

            #1
            if (out != data[i][1])
            begin
                $display($time,, "Error: expected=%b, got=%b", data[i][1], out);
                error = 1;
            end
        end

        if (error)
            $display("Tests failed!");
        else
            $display("Tests passed!");

        $finish;
    end

    initial begin
        $dumpfile("debouncer.vcd");
        $dumpvars(0, debouncer_tb);
    end
endmodule

seminars/week06/debouncer/debouncer.vcd
$date
	Wed Dec 20 18:22:20 2023
$end
$version
	Icarus Verilog
$end
$timescale
	1ns
$end
$scope module debouncer_tb $end
$var wire 1 ! out $end
$var reg 1 " clk $end
$var reg 1 # clken $end
$var reg 1 $ error $end
$var reg 1 % in $end
$var integer 32 & i [31:0] $end
$scope module db $end
$var wire 1 " clk $end
$var wire 1 # clken $end
$var wire 1 % in $end
$var reg 2 ' counter [1:0] $end
$var reg 1 ! out $end
$upscope $end
$upscope $end
$enddefinitions $end
#0
$dumpvars
b0 '
b0 &
0%
0$
1#
0"
0!
$end
#5
b1 '
1%
1"
#6
b1 &
#10
0"
#15
b10 '
1"
#16
b10 &
#20
0"
#25
b0 '
0%
1"
#26
b11 &
#30
0"
#35
b1 '
1"
#36
b100 &
#40
0"
#45
b10 '
1"
#46
b101 &
#50
0"
#55
1!
b0 '
1%
1"
#56
b110 &
#60
0"
#65
b1 '
0%
1"
#66
b111 &
#70
0"
#75
b10 '
1%
1"
#76
b1000 &
#80
0"
#85
0!
b0 '
0%
1"
#86
b1001 &
#90
0"
#95
b1 '
1%
1"
#96
b1010 &
#100
0"
#105
b10 '
0%
1"
#106
b1011 &
#110
0"
#115
1!
b0 '
1%
1"
#116
b1100 &
#120
0"
#125
b1 '
0%
1"
#126
b1101 &
#130
0"
#135
b10 '
1"
#136
b1110 &
#140
0"
#145
b0 '
1%
1"
#146
b1111 &
#150
0"
#155
b1 '
0%
1"
#156
b10000 &
#160
0"
#165
b10 '
1"
#166
b10001 &
#170
0"
#175
0!
b0 '
1"
#176
b10010 &
#180
0"
#185
b1 '
1%
1"
#186
b10011 &
#190
0"
#195
b10 '
1"
#196
b10100 &
