seminars/week06/timer/timer.v
module timer #(parameter WIDTH = 32, parameter PERIOD = 1000)(
	input  clk,
	output out);

    reg [WIDTH - 1:0] counter;

    assign out = counter == PERIOD - 1;

    always @(posedge clk)
        counter <= out ? 0 : counter + 1;
endmodule

seminars/week06/timer/timer_tb.v
`timescale 1ns/1ns

module timer_tb;
    parameter PERIOD        = 10;
    parameter TIMER_PERIOD  = 3;
    parameter TIMER_WIDTH   = 2;

    integer i;

    reg                     clk;
    reg                     error;
    reg [TIMER_WIDTH - 1:0] counter;

    wire out;

    timer #(.WIDTH(TIMER_WIDTH), .PERIOD(TIMER_PERIOD)) t(.clk(clk), .out(out));

    initial begin
        clk     = 0;
        error   = 0;
        counter = 0;

        // There might be a problem in case of different solutions
        t.counter = 0;
    end

    initial
        forever #(PERIOD / 2.0)
            clk = ~clk;

    initial begin
        @(posedge out);

        for (i = 0; i < TIMER_PERIOD * 3; i += 1)
        begin
            @(posedge clk) #1
            counter += 1;

            if ((out && counter < TIMER_PERIOD) || (!out && counter >= TIMER_PERIOD))
            begin
                error = 1;
                $display($time,, "Error: expected=%b, got=%b", 1, out);
            end

            if (out)
                counter = 0;
        end

        if (error)
            $display("Tests failed!");
        else
            $display("Tests passed!");

        $finish;
    end

    initial begin
        $dumpfile("timer.vcd");
        $dumpvars(0, timer_tb);
    end
endmodule

seminars/week06/timer/timer.vcd
$date
	Wed Dec 20 20:46:31 2023
$end
$version
	Icarus Verilog
$end
$timescale
	1ns
$end
$scope module timer_tb $end
$var wire 1 ! out $end
$var reg 1 " clk $end
$var reg 2 # counter [1:0] $end
$var reg 1 $ error $end
$var integer 32 % i [31:0] $end
$scope module t $end
$var wire 1 " clk $end
$var wire 1 ! out $end
$var reg 2 & counter [1:0] $end
$upscope $end
$upscope $end
$enddefinitions $end
#0
$dumpvars
b0 &
bx %
0$
b0 #
0"
0!
$end
#5
b1 &
1"
#10
0"
#15
b0 %
1!
b10 &
1"
#20
0"
#25
0!
b0 &
1"
#26
b1 %
b1 #
#30
0"
#35
b1 &
1"
#36
b10 %
b10 #
#40
0"
#45
1!
b10 &
1"
#46
b11 %
b0 #
#50
0"
#55
0!
b0 &
1"
#56
b100 %
b1 #
#60
0"
#65
b1 &
1"
#66
b101 %
b10 #
#70
0"
#75
1!
b10 &
1"
#76
b110 %
b0 #
#80
0"
#85
0!
b0 &
1"
#86
b111 %
b1 #
#90
0"
#95
b1 &
1"
#96
b1000 %
b10 #
#100
0"
#105
1!
b10 &
1"
#106
b1001 %
b0 #
