seminars/week06/segment7/segment7.v
// module for translating 4-bit number to the 7-segment display
module segment7 (
	input 				enable,  // enable of the display, active 1
	input       [3:0]	data,    // input data
	output reg	[6:0]	seg		 // display's segments, active 0
    );

	always @(*)
		if (enable)
			case (data)
				4'h0   : seg = 7'b1000000;
				4'h1   : seg = 7'b1111001;
				4'h2   : seg = 7'b0100100;
				4'h3   : seg = 7'b0110000;
				4'h4   : seg = 7'b0011001;
				4'h5   : seg = 7'b0010010;
				4'h6   : seg = 7'b0000010;
				4'h7   : seg = 7'b1111000;
				4'h8   : seg = 7'b0000000;
				4'h9   : seg = 7'b0011000;
				4'hA   : seg = 7'b0001000;
				4'hb   : seg = 7'b0000011;
				4'hC   : seg = 7'b1000110;
				4'hd   : seg = 7'b0100001;
				4'hE   : seg = 7'b0000110;
				4'hF   : seg = 7'b0001110;
				default: seg = 7'b1111111;
			endcase
		else
			seg = 7'b1111111;
endmodule

seminars/week06/segment7/segment7_tb.v
`timescale 1ns/1ns

module segment7_tb;
    integer i;

    reg         enable;
    reg         error;
    reg [3:0]   data;
    reg [6:0]   expected;

    wire [6:0] out;

    segment7 s7(.enable(enable), .data(data), .seg(out));

    initial begin
        enable  = 1;
        error   = 0;

        for (i = 0; i < 16; i += 1)
        begin
            #1
            data = i;

            // Test combinations:
            #1
            // Possible to use case instead of another mem file
			case (data)
				4'h0   : expected = 7'b1000000;
				4'h1   : expected = 7'b1111001;
				4'h2   : expected = 7'b0100100;
				4'h3   : expected = 7'b0110000;
				4'h4   : expected = 7'b0011001;
				4'h5   : expected = 7'b0010010;
				4'h6   : expected = 7'b0000010;
				4'h7   : expected = 7'b1111000;
				4'h8   : expected = 7'b0000000;
				4'h9   : expected = 7'b0011000;
				4'hA   : expected = 7'b0001000;
				4'hb   : expected = 7'b0000011;
				4'hC   : expected = 7'b1000110;
				4'hd   : expected = 7'b0100001;
				4'hE   : expected = 7'b0000110;
				4'hF   : expected = 7'b0001110;
				default: expected = 7'b1111111;
			endcase

            if (out != expected)
            begin
                error = 1;
                $display("Error: input=%h, output=%b, expected=%b", data, out, expected);
            end
        end

        // Test enable:
        #1
        data    = 0;
        enable  = 0;

        #1
        if (!(&out))
            $display("Error: enable won't turn off segment!");

        if (error)
            $display("Test failed!");
        else
            $display("Test passed!");

        $finish;
    end

    initial begin
        $dumpfile("segment7.vcd");
        $dumpvars(0, segment7_tb);
    end
endmodule

seminars/week06/segment7/segment7.vcd
$date
	Wed Dec 20 19:52:06 2023
$end
$version
	Icarus Verilog
$end
$timescale
	1ns
$end
$scope module segment7_tb $end
$var wire 7 ! out [6:0] $end
$var reg 4 " data [3:0] $end
$var reg 1 # enable $end
$var reg 1 $ error $end
$var reg 7 % expected [6:0] $end
$var integer 32 & i [31:0] $end
$scope module s7 $end
$var wire 4 ' data [3:0] $end
$var wire 1 # enable $end
$var reg 7 ( seg [6:0] $end
$upscope $end
$upscope $end
$enddefinitions $end
#0
$dumpvars
b1111111 (
bx '
b0 &
bx %
0$
1#
bx "
b1111111 !
$end
#1
b1000000 !
b1000000 (
b0 "
b0 '
#2
b1 &
b1000000 %
#3
b1111001 !
b1111001 (
b1 "
b1 '
#4
b10 &
b1111001 %
#5
b100100 !
b100100 (
b10 "
b10 '
#6
b11 &
b100100 %
#7
b110000 !
b110000 (
b11 "
b11 '
#8
b100 &
b110000 %
#9
b11001 !
b11001 (
b100 "
b100 '
#10
b101 &
b11001 %
#11
b10010 !
b10010 (
b101 "
b101 '
#12
b110 &
b10010 %
#13
b10 !
b10 (
b110 "
b110 '
#14
b111 &
b10 %
#15
b1111000 !
b1111000 (
b111 "
b111 '
#16
b1000 &
b1111000 %
#17
b0 !
b0 (
b1000 "
b1000 '
#18
b1001 &
b0 %
#19
b11000 !
b11000 (
b1001 "
b1001 '
#20
b1010 &
b11000 %
#21
b1000 !
b1000 (
b1010 "
b1010 '
#22
b1011 &
b1000 %
#23
b11 !
b11 (
b1011 "
b1011 '
#24
b1100 &
b11 %
#25
b1000110 !
b1000110 (
b1100 "
b1100 '
#26
b1101 &
b1000110 %
#27
b100001 !
b100001 (
b1101 "
b1101 '
#28
b1110 &
b100001 %
#29
b110 !
b110 (
b1110 "
b1110 '
#30
b1111 &
b110 %
#31
b1110 !
b1110 (
b1111 "
b1111 '
#32
b10000 &
b1110 %
#33
b1111111 !
b1111111 (
0#
b0 "
b0 '
