seminars/week06/pwm/pwm.v
module pwm(
	input 		clk,   // input clock
	input 		clken, // input clock enable
	input [7:0] duty,  // duty cycle
	output reg 	out	   // generated signal
	);

	reg [7:0] counter;

	always @(posedge clk)
        if (clken)
        begin
            counter <= counter + 1;
            out     <= &duty ? 1 : counter < duty;
        end
endmodule

seminars/week06/pwm/pwm_tb.v
`timescale 1ns/1ns

module pwm_tb;
    parameter PERIOD     = 10;
    parameter TEST_COUNT = 20;

    integer i;
    integer j;

    reg         clk;
    reg         clken;
    reg [7:0]   duty;
    reg [7:0]   counter;
    reg         error;

    wire out;

    pwm p(.clk(clk), .clken(clken), .duty(duty), .out(out));

    initial begin
        clk     = 0;
        clken   = 1;
        error   = 0;

        p.counter = 255;
    end

    initial
        forever #(PERIOD / 2.0)
            clk = ~clk;

    initial begin
        // Testing specific duty cycle
        duty        = 42;
        p.counter   = 255;

        for (j = 0; j < 2; j += 1)
        begin
            counter = 0;

            for (i = 0; i < 256; i += 1)
            begin
                @(posedge clk) #1
                counter += out;
            end

            error = error | (counter != duty);
        end

        if (error)
            $display("Error: Pwm wasn't set exactly for given pwm duty cycle!");

        // Testing zero duty cycle
        duty = 0;

        for (i = 0; i < 1024; i += 1)
        begin
            @(posedge clk) #1
            error = error | out;
        end

        if (error)
            $display("Error: there was a pulse durning zero duty cycle!");

        error = 0;

        // Testing full duty cycle
        duty = 255;

        for (i = 0; i < 1024; i += 1)
        begin
            @(posedge clk) #1
            error = error | !out;
        end

        if (error)
            $display("Error: out wasn't held up continuously durning full duty cycle!");

        // Testing clken
        clken   = 0;
        duty    = 0;

        @(posedge clk) #1
        if (!out)
            $display("Error: clken might not work properly!");

        $finish;
    end

    initial begin
        $dumpfile("pwm.vcd");
        $dumpvars(0, pwm_tb);
    end
endmodule

seminars/week06/pwm/pwm.vcd
$date
	Wed Dec 20 19:32:55 2023
$end
$version
	Icarus Verilog
$end
$timescale
	1ns
$end
$scope module pwm_tb $end
$var wire 1 ! out $end
$var reg 1 " clk $end
$var reg 1 # clken $end
$var reg 8 $ counter [7:0] $end
$var reg 8 % duty [7:0] $end
$var reg 1 & error $end
$var integer 32 ' i [31:0] $end
$var integer 32 ( j [31:0] $end
$scope module p $end
$var wire 1 " clk $end
$var wire 1 # clken $end
$var wire 8 ) duty [7:0] $end
$var reg 8 * counter [7:0] $end
$var reg 1 ! out $end
$upscope $end
$upscope $end
$enddefinitions $end
#0
$dumpvars
b11111111 *
b101010 )
b0 (
b0 '
0&
b101010 %
b0 $
1#
0"
x!
$end
#5
0!
b0 *
1"
#6
b1 '
#10
0"
#15
1!
b1 *
1"
#16
b10 '
b1 $
#20
0"
#25
b10 *
1"
#26
b11 '
b10 $
#30
0"
#35
b11 *
1"
#36
b100 '
b11 $
#40
0"
#45
b100 *
1"
#46
b101 '
b100 $
#50
0"
#55
b101 *
1"
#56
b110 '
b101 $
#60
0"
#65
b110 *
1"
#66
b111 '
b110 $
#70
0"
#75
b111 *
1"
#76
b1000 '
b111 $
#80
0"
#85
b1000 *
1"
#86
b1001 '
b1000 $
#90
0"
#95
b1001 *
1"
#96
b1010 '
b1001 $
#100
0"
#105
b1010 *
1"
#106
b1011 '
b1010 $
#110
0"
#115
b1011 *
1"
#116
b1100 '
b1011 $
#120
0"
#125
b1100 *
1"
#126
b1101 '
b1100 $
#130
0"
#135
b1101 *
1"
#136
b1110 '
b1101 $
#140
0"
#145
b1110 *
1"
#146
b1111 '
b1110 $
#150
0"
#155
b1111 *
1"
#156
b10000 '
b1111 $
#160
0"
#165
b10000 *
1"
#166
b10001 '
b10000 $
#170
0"
#175
b10001 *
1"
#176
b10010 '
b10001 $
#180
0"
#185
b10010 *
1"
#186
b10011 '
b10010 $
#190
0"
#195
b10011 *
1"
#196
b10100 '
b10011 $
#200
0"
#205
b10100 *
1"
#206
b10101 '
b10100 $
#210
0"
#215
b10101 *
1"
#216
b10110 '
b10101 $
#220
0"
#225
b10110 *
1"
#226
b10111 '
b10110 $
#230
0"
#235
b10111 *
1"
#236
b11000 '
b10111 $
#240
0"
#245
b11000 *
1"
#246
b11001 '
b11000 $
#250
0"
#255
b11001 *
1"
#256
b11010 '
b11001 $
#260
0"
#265
b11010 *
1"
#266
b11011 '
b11010 $
#270
0"
#275
b11011 *
1"
#276
b11100 '
b11011 $
#280
0"
#285
b11100 *
1"
#286
b11101 '
b11100 $
#290
0"
#295
b11101 *
1"
#296
b11110 '
b11101 $
#300
0"
#305
b11110 *
1"
#306
b11111 '
b11110 $
#310
0"
#315
b11111 *
1"
#316
b100000 '
b11111 $
#320
0"
#325
b100000 *
1"
#326
b100001 '
b100000 $
#330
0"
#335
b100001 *
1"
#336
b100010 '
b100001 $
#340
0"
#345
b100010 *
1"
#346
b100011 '
b100010 $
#350
0"
#355
b100011 *
1"
#356
b100100 '
b100011 $
#360
0"
#365
b100100 *
1"
#366
b100101 '
b100100 $
#370
0"
#375
b100101 *
1"
#376
b100110 '
b100101 $
#380
0"
#385
b100110 *
1"
#386
b100111 '
b100110 $
#390
0"
#395
b100111 *
1"
#396
b101000 '
b100111 $
#400
0"
#405
b101000 *
1"
#406
b101001 '
b101000 $
#410
0"
#415
b101001 *
1"
#416
b101010 '
b101001 $
#420
0"
#425
b101010 *
1"
#426
b101011 '
b101010 $
#430
0"
#435
0!
b101011 *
1"
#436
b101100 '
#440
0"
#445
b101100 *
1"
#446
b101101 '
#450
0"
#455
b101101 *
1"
#456
b101110 '
#460
0"
#465
b101110 *
1"
#466
b101111 '
#470
0"
#475
b101111 *
1"
#476
b110000 '
#480
0"
#485
b110000 *
1"
#486
b110001 '
#490
0"
#495
b110001 *
1"
#496
b110010 '
#500
0"
#505
b110010 *
1"
#506
b110011 '
#510
0"
#515
b110011 *
1"
#516
b110100 '
#520
0"
#525
b110100 *
1"
#526
b110101 '
#530
0"
#535
b110101 *
1"
#536
b110110 '
#540
0"
#545
b110110 *
1"
#546
b110111 '
#550
0"
#555
b110111 *
1"
#556
b111000 '
#560
0"
#565
b111000 *
1"
#566
b111001 '
#570
0"
#575
b111001 *
1"
#576
b111010 '
#580
0"
#585
b111010 *
1"
#586
b111011 '
#590
0"
#595
b111011 *
1"
#596
b111100 '
#600
0"
#605
b111100 *
1"
#606
b111101 '
#610
0"
#615
b111101 *
1"
#616
b111110 '
#620
0"
#625
b111110 *
1"
#626
b111111 '
#630
0"
#635
b111111 *
1"
#636
b1000000 '
#640
0"
#645
b1000000 *
1"
#646
b1000001 '
#650
0"
#655
b1000001 *
1"
#656
b1000010 '
#660
0"
#665
b1000010 *
1"
#666
b1000011 '
#670
0"
#675
b1000011 *
1"
#676
b1000100 '
#680
0"
#685
b1000100 *
1"
#686
b1000101 '
#690
0"
#695
b1000101 *
1"
#696
b1000110 '
#700
0"
#705
b1000110 *
1"
#706
b1000111 '
#710
0"
#715
b1000111 *
1"
#716
b1001000 '
#720
0"
#725
b1001000 *
1"
#726
b1001001 '
#730
0"
#735
b1001001 *
1"
#736
b1001010 '
#740
0"
#745
b1001010 *
1"
#746
b1001011 '
#750
0"
#755
b1001011 *
1"
#756
b1001100 '
#760
0"
#765
b1001100 *
1"
#766
b1001101 '
#770
0"
#775
b1001101 *
1"
#776
b1001110 '
#780
0"
#785
b1001110 *
1"
#786
b1001111 '
#790
0"
#795
b1001111 *
1"
#796
b1010000 '
#800
0"
#805
b1010000 *
1"
#806
b1010001 '
#810
0"
#815
b1010001 *
1"
#816
b1010010 '
#820
0"
#825
b1010010 *
1"
#826
b1010011 '
#830
0"
#835
b1010011 *
1"
#836
b1010100 '
#840
0"
#845
b1010100 *
1"
#846
b1010101 '
#850
0"
#855
b1010101 *
1"
#856
b1010110 '
#860
0"
#865
b1010110 *
1"
#866
b1010111 '
#870
0"
#875
b1010111 *
1"
#876
b1011000 '
#880
0"
#885
b1011000 *
1"
#886
b1011001 '
#890
0"
#895
b1011001 *
1"
#896
b1011010 '
#900
0"
#905
b1011010 *
1"
#906
b1011011 '
#910
0"
#915
b1011011 *
1"
#916
b1011100 '
#920
0"
#925
b1011100 *
1"
#926
b1011101 '
#930
0"
#935
b1011101 *
1"
#936
b1011110 '
#940
0"
#945
b1011110 *
1"
#946
b1011111 '
#950
0"
#955
b1011111 *
1"
#956
b1100000 '
#960
0"
#965
b1100000 *
1"
#966
b1100001 '
#970
0"
#975
b1100001 *
1"
#976
b1100010 '
#980
0"
#985
b1100010 *
1"
#986
b1100011 '
#990
0"
#995
b1100011 *
1"
#996
b1100100 '
#1000
0"
#1005
b1100100 *
1"
#1006
b1100101 '
#1010
0"
#1015
b1100101 *
1"
#1016
b1100110 '
#1020
0"
#1025
b1100110 *
1"
#1026
b1100111 '
#1030
0"
#1035
b1100111 *
1"
#1036
b1101000 '
#1040
0"
#1045
b1101000 *
1"
#1046
b1101001 '
#1050
0"
#1055
b1101001 *
1"
#1056
b1101010 '
#1060
0"
#1065
b1101010 *
1"
#1066
b1101011 '
#1070
0"
#1075
b1101011 *
1"
#1076
b1101100 '
#1080
0"
#1085
b1101100 *
1"
#1086
b1101101 '
#1090
0"
#1095
b1101101 *
1"
#1096
b1101110 '
#1100
0"
#1105
b1101110 *
1"
#1106
b1101111 '
#1110
0"
#1115
b1101111 *
1"
#1116
b1110000 '
#1120
0"
#1125
b1110000 *
1"
#1126
b1110001 '
#1130
0"
#1135
b1110001 *
1"
#1136
b1110010 '
#1140
0"
#1145
b1110010 *
1"
#1146
b1110011 '
#1150
0"
#1155
b1110011 *
1"
#1156
b1110100 '
#1160
0"
#1165
b1110100 *
1"
#1166
b1110101 '
#1170
0"
#1175
b1110101 *
1"
#1176
b1110110 '
#1180
0"
#1185
b1110110 *
1"
#1186
b1110111 '
#1190
0"
#1195
b1110111 *
1"
#1196
b1111000 '
#1200
0"
#1205
b1111000 *
1"
#1206
b1111001 '
#1210
0"
#1215
b1111001 *
1"
#1216
b1111010 '
#1220
0"
#1225
b1111010 *
1"
#1226
b1111011 '
#1230
0"
#1235
b1111011 *
1"
#1236
b1111100 '
#1240
0"
#1245
b1111100 *
1"
#1246
b1111101 '
#1250
0"
#1255
b1111101 *
1"
#1256
b1111110 '
#1260
0"
#1265
b1111110 *
1"
#1266
b1111111 '
#1270
0"
#1275
b1111111 *
1"
#1276
b10000000 '
#1280
0"
#1285
b10000000 *
1"
#1286
b10000001 '
#1290
0"
#1295
b10000001 *
1"
#1296
b10000010 '
#1300
0"
#1305
b10000010 *
1"
#1306
b10000011 '
#1310
0"
#1315
b10000011 *
1"
#1316
b10000100 '
#1320
0"
#1325
b10000100 *
1"
#1326
b10000101 '
#1330
0"
#1335
b10000101 *
1"
#1336
b10000110 '
#1340
0"
#1345
b10000110 *
1"
#1346
b10000111 '
#1350
0"
#1355
b10000111 *
1"
#1356
b10001000 '
#1360
0"
#1365
b10001000 *
1"
#1366
b10001001 '
#1370
0"
#1375
b10001001 *
1"
#1376
b10001010 '
#1380
0"
#1385
b10001010 *
1"
#1386
b10001011 '
#1390
0"
#1395
b10001011 *
1"
#1396
b10001100 '
#1400
0"
#1405
b10001100 *
1"
#1406
b10001101 '
#1410
0"
#1415
b10001101 *
1"
#1416
b10001110 '
#1420
0"
#1425
b10001110 *
1"
#1426
b10001111 '
#1430
0"
#1435
b10001111 *
1"
#1436
b10010000 '
#1440
0"
#1445
b10010000 *
1"
#1446
b10010001 '
#1450
0"
#1455
b10010001 *
1"
#1456
b10010010 '
#1460
0"
#1465
b10010010 *
1"
#1466
b10010011 '
#1470
0"
#1475
b10010011 *
1"
#1476
b10010100 '
#1480
0"
#1485
b10010100 *
1"
#1486
b10010101 '
#1490
0"
#1495
b10010101 *
1"
#1496
b10010110 '
#1500
0"
#1505
b10010110 *
1"
#1506
b10010111 '
#1510
0"
#1515
b10010111 *
1"
#1516
b10011000 '
#1520
0"
#1525
b10011000 *
1"
#1526
b10011001 '
#1530
0"
#1535
b10011001 *
1"
#1536
b10011010 '
#1540
0"
#1545
b10011010 *
1"
#1546
b10011011 '
#1550
0"
#1555
b10011011 *
1"
#1556
b10011100 '
#1560
0"
#1565
b10011100 *
1"
#1566
b10011101 '
#1570
0"
#1575
b10011101 *
1"
#1576
b10011110 '
#1580
0"
#1585
b10011110 *
1"
#1586
b10011111 '
#1590
0"
#1595
b10011111 *
1"
#1596
b10100000 '
#1600
0"
#1605
b10100000 *
1"
#1606
b10100001 '
#1610
0"
#1615
b10100001 *
1"
#1616
b10100010 '
#1620
0"
#1625
b10100010 *
1"
#1626
b10100011 '
#1630
0"
#1635
b10100011 *
1"
#1636
b10100100 '
#1640
0"
#1645
b10100100 *
1"
#1646
b10100101 '
#1650
0"
#1655
b10100101 *
1"
#1656
b10100110 '
#1660
0"
#1665
b10100110 *
1"
#1666
b10100111 '
#1670
0"
#1675
b10100111 *
1"
#1676
b10101000 '
#1680
0"
#1685
b10101000 *
1"
#1686
b10101001 '
#1690
0"
#1695
b10101001 *
1"
#1696
b10101010 '
#1700
0"
#1705
b10101010 *
1"
#1706
b10101011 '
#1710
0"
#1715
b10101011 *
1"
#1716
b10101100 '
#1720
0"
#1725
b10101100 *
1"
#1726
b10101101 '
#1730
0"
#1735
b10101101 *
1"
#1736
b10101110 '
#1740
0"
#1745
b10101110 *
1"
#1746
b10101111 '
#1750
0"
#1755
b10101111 *
1"
#1756
b10110000 '
#1760
0"
#1765
b10110000 *
1"
#1766
b10110001 '
#1770
0"
#1775
b10110001 *
1"
#1776
b10110010 '
#1780
0"
#1785
b10110010 *
1"
#1786
b10110011 '
#1790
0"
#1795
b10110011 *
1"
#1796
b10110100 '
#1800
0"
#1805
b10110100 *
1"
#1806
b10110101 '
#1810
0"
#1815
b10110101 *
1"
#1816
b10110110 '
#1820
0"
#1825
b10110110 *
1"
#1826
b10110111 '
#1830
0"
#1835
b10110111 *
1"
#1836
b10111000 '
#1840
0"
#1845
b10111000 *
1"
#1846
b10111001 '
#1850
0"
#1855
b10111001 *
1"
#1856
b10111010 '
#1860
0"
#1865
b10111010 *
1"
#1866
b10111011 '
#1870
0"
#1875
b10111011 *
1"
#1876
b10111100 '
#1880
0"
#1885
b10111100 *
1"
#1886
b10111101 '
#1890
0"
#1895
b10111101 *
1"
#1896
b10111110 '
#1900
0"
#1905
b10111110 *
1"
#1906
b10111111 '
#1910
0"
#1915
b10111111 *
1"
#1916
b11000000 '
#1920
0"
#1925
b11000000 *
1"
#1926
b11000001 '
#1930
0"
#1935
b11000001 *
1"
#1936
b11000010 '
#1940
0"
#1945
b11000010 *
1"
#1946
b11000011 '
#1950
0"
#1955
b11000011 *
1"
#1956
b11000100 '
#1960
0"
#1965
b11000100 *
1"
#1966
b11000101 '
#1970
0"
#1975
b11000101 *
1"
#1976
b11000110 '
#1980
0"
#1985
b11000110 *
1"
#1986
b11000111 '
#1990
0"
#1995
b11000111 *
1"
#1996
b11001000 '
#2000
0"
#2005
b11001000 *
1"
#2006
b11001001 '
#2010
0"
#2015
b11001001 *
1"
#2016
b11001010 '
#2020
0"
#2025
b11001010 *
1"
#2026
b11001011 '
#2030
0"
#2035
b11001011 *
1"
#2036
b11001100 '
#2040
0"
#2045
b11001100 *
1"
#2046
b11001101 '
#2050
0"
#2055
b11001101 *
1"
#2056
b11001110 '
#2060
0"
#2065
b11001110 *
1"
#2066
b11001111 '
#2070
0"
#2075
b11001111 *
1"
#2076
b11010000 '
#2080
0"
#2085
b11010000 *
1"
#2086
b11010001 '
#2090
0"
#2095
b11010001 *
1"
#2096
b11010010 '
#2100
0"
#2105
b11010010 *
1"
#2106
b11010011 '
#2110
0"
#2115
b11010011 *
1"
#2116
b11010100 '
#2120
0"
#2125
b11010100 *
1"
#2126
b11010101 '
#2130
0"
#2135
b11010101 *
1"
#2136
b11010110 '
#2140
0"
#2145
b11010110 *
1"
#2146
b11010111 '
#2150
0"
#2155
b11010111 *
1"
#2156
b11011000 '
#2160
0"
#2165
b11011000 *
1"
#2166
b11011001 '
#2170
0"
#2175
b11011001 *
1"
#2176
b11011010 '
#2180
0"
#2185
b11011010 *
1"
#2186
b11011011 '
#2190
0"
#2195
b11011011 *
1"
#2196
b11011100 '
#2200
0"
#2205
b11011100 *
1"
#2206
b11011101 '
#2210
0"
#2215
b11011101 *
1"
#2216
b11011110 '
#2220
0"
#2225
b11011110 *
1"
#2226
b11011111 '
#2230
0"
#2235
b11011111 *
1"
#2236
b11100000 '
#2240
0"
#2245
b11100000 *
1"
#2246
b11100001 '
#2250
0"
#2255
b11100001 *
1"
#2256
b11100010 '
#2260
0"
#2265
b11100010 *
1"
#2266
b11100011 '
#2270
0"
#2275
b11100011 *
1"
#2276
b11100100 '
#2280
0"
#2285
b11100100 *
1"
#2286
b11100101 '
#2290
0"
#2295
b11100101 *
1"
#2296
b11100110 '
#2300
0"
#2305
b11100110 *
1"
#2306
b11100111 '
#2310
0"
#2315
b11100111 *
1"
#2316
b11101000 '
#2320
0"
#2325
b11101000 *
1"
#2326
b11101001 '
#2330
0"
#2335
b11101001 *
1"
#2336
b11101010 '
#2340
0"
#2345
b11101010 *
1"
#2346
b11101011 '
#2350
0"
#2355
b11101011 *
1"
#2356
b11101100 '
#2360
0"
#2365
b11101100 *
1"
#2366
b11101101 '
#2370
0"
#2375
b11101101 *
1"
#2376
b11101110 '
#2380
0"
#2385
b11101110 *
1"
#2386
b11101111 '
#2390
0"
#2395
b11101111 *
1"
#2396
b11110000 '
#2400
0"
#2405
b11110000 *
1"
#2406
b11110001 '
#2410
0"
#2415
b11110001 *
1"
#2416
b11110010 '
#2420
0"
#2425
b11110010 *
1"
#2426
b11110011 '
#2430
0"
#2435
b11110011 *
1"
#2436
b11110100 '
#2440
0"
#2445
b11110100 *
1"
#2446
b11110101 '
#2450
0"
#2455
b11110101 *
1"
#2456
b11110110 '
#2460
0"
#2465
b11110110 *
1"
#2466
b11110111 '
#2470
0"
#2475
b11110111 *
1"
#2476
b11111000 '
#2480
0"
#2485
b11111000 *
1"
#2486
b11111001 '
#2490
0"
#2495
b11111001 *
1"
#2496
b11111010 '
#2500
0"
#2505
b11111010 *
1"
#2506
b11111011 '
#2510
0"
#2515
b11111011 *
1"
#2516
b11111100 '
#2520
0"
#2525
b11111100 *
1"
#2526
b11111101 '
#2530
0"
#2535
b11111101 *
1"
#2536
b11111110 '
#2540
0"
#2545
b11111110 *
1"
#2546
b11111111 '
#2550
0"
#2555
b11111111 *
1"
#2556
b0 $
b1 (
b0 '
#2560
0"
#2565
b0 *
1"
#2566
b1 '
#2570
0"
#2575
1!
b1 *
1"
#2576
b10 '
b1 $
#2580
0"
#2585
b10 *
1"
#2586
b11 '
b10 $
#2590
0"
#2595
b11 *
1"
#2596
b100 '
b11 $
#2600
0"
#2605
b100 *
1"
#2606
b101 '
b100 $
#2610
0"
#2615
b101 *
1"
#2616
b110 '
b101 $
#2620
0"
#2625
b110 *
1"
#2626
b111 '
b110 $
#2630
0"
#2635
b111 *
1"
#2636
b1000 '
b111 $
#2640
0"
#2645
b1000 *
1"
#2646
b1001 '
b1000 $
#2650
0"
#2655
b1001 *
1"
#2656
b1010 '
b1001 $
#2660
0"
#2665
b1010 *
1"
#2666
b1011 '
b1010 $
#2670
0"
#2675
b1011 *
1"
#2676
b1100 '
b1011 $
#2680
0"
#2685
b1100 *
1"
#2686
b1101 '
b1100 $
#2690
0"
#2695
b1101 *
1"
#2696
b1110 '
b1101 $
#2700
0"
#2705
b1110 *
1"
#2706
b1111 '
b1110 $
#2710
0"
#2715
b1111 *
1"
#2716
b10000 '
b1111 $
#2720
0"
#2725
b10000 *
1"
#2726
b10001 '
b10000 $
#2730
0"
#2735
b10001 *
1"
#2736
b10010 '
b10001 $
#2740
0"
#2745
b10010 *
1"
#2746
b10011 '
b10010 $
#2750
0"
#2755
b10011 *
1"
#2756
b10100 '
b10011 $
#2760
0"
#2765
b10100 *
1"
#2766
b10101 '
b10100 $
#2770
0"
#2775
b10101 *
1"
#2776
b10110 '
b10101 $
#2780
0"
#2785
b10110 *
1"
#2786
b10111 '
b10110 $
#2790
0"
#2795
b10111 *
1"
#2796
b11000 '
b10111 $
#2800
0"
#2805
b11000 *
1"
#2806
b11001 '
b11000 $
#2810
0"
#2815
b11001 *
1"
#2816
b11010 '
b11001 $
#2820
0"
#2825
b11010 *
1"
#2826
b11011 '
b11010 $
#2830
0"
#2835
b11011 *
1"
#2836
b11100 '
b11011 $
#2840
0"
#2845
b11100 *
1"
#2846
b11101 '
b11100 $
#2850
0"
#2855
b11101 *
1"
#2856
b11110 '
b11101 $
#2860
0"
#2865
b11110 *
1"
#2866
b11111 '
b11110 $
#2870
0"
#2875
b11111 *
1"
#2876
b100000 '
b11111 $
#2880
0"
#2885
b100000 *
1"
#2886
b100001 '
b100000 $
#2890
0"
#2895
b100001 *
1"
#2896
b100010 '
b100001 $
#2900
0"
#2905
b100010 *
1"
#2906
b100011 '
b100010 $
#2910
0"
#2915
b100011 *
1"
#2916
b100100 '
b100011 $
#2920
0"
#2925
b100100 *
1"
#2926
b100101 '
b100100 $
#2930
0"
#2935
b100101 *
1"
#2936
b100110 '
b100101 $
#2940
0"
#2945
b100110 *
1"
#2946
b100111 '
b100110 $
#2950
0"
#2955
b100111 *
1"
#2956
b101000 '
b100111 $
#2960
0"
#2965
b101000 *
1"
#2966
b101001 '
b101000 $
#2970
0"
#2975
b101001 *
1"
#2976
b101010 '
b101001 $
#2980
0"
#2985
b101010 *
1"
#2986
b101011 '
b101010 $
#2990
0"
#2995
0!
b101011 *
1"
#2996
b101100 '
#3000
0"
#3005
b101100 *
1"
#3006
b101101 '
#3010
0"
#3015
b101101 *
1"
#3016
b101110 '
#3020
0"
#3025
b101110 *
1"
#3026
b101111 '
#3030
0"
#3035
b101111 *
1"
#3036
b110000 '
#3040
0"
#3045
b110000 *
1"
#3046
b110001 '
#3050
0"
#3055
b110001 *
1"
#3056
b110010 '
#3060
0"
#3065
b110010 *
1"
#3066
b110011 '
#3070
0"
#3075
b110011 *
1"
#3076
b110100 '
#3080
0"
#3085
b110100 *
1"
#3086
b110101 '
#3090
0"
#3095
b110101 *
1"
#3096
b110110 '
#3100
0"
#3105
b110110 *
1"
#3106
b110111 '
#3110
0"
#3115
b110111 *
1"
#3116
b111000 '
#3120
0"
#3125
b111000 *
1"
#3126
b111001 '
#3130
0"
#3135
b111001 *
1"
#3136
b111010 '
#3140
0"
#3145
b111010 *
1"
#3146
b111011 '
#3150
0"
#3155
b111011 *
1"
#3156
b111100 '
#3160
0"
#3165
b111100 *
1"
#3166
b111101 '
#3170
0"
#3175
b111101 *
1"
#3176
b111110 '
#3180
0"
#3185
b111110 *
1"
#3186
b111111 '
#3190
0"
#3195
b111111 *
1"
#3196
b1000000 '
#3200
0"
#3205
b1000000 *
1"
#3206
b1000001 '
#3210
0"
#3215
b1000001 *
1"
#3216
b1000010 '
#3220
0"
#3225
b1000010 *
1"
#3226
b1000011 '
#3230
0"
#3235
b1000011 *
1"
#3236
b1000100 '
#3240
0"
#3245
b1000100 *
1"
#3246
b1000101 '
#3250
0"
#3255
b1000101 *
1"
#3256
b1000110 '
#3260
0"
#3265
b1000110 *
1"
#3266
b1000111 '
#3270
0"
#3275
b1000111 *
1"
#3276
b1001000 '
#3280
0"
#3285
b1001000 *
1"
#3286
b1001001 '
#3290
0"
#3295
b1001001 *
1"
#3296
b1001010 '
#3300
0"
#3305
b1001010 *
1"
#3306
b1001011 '
#3310
0"
#3315
b1001011 *
1"
#3316
b1001100 '
#3320
0"
#3325
b1001100 *
1"
#3326
b1001101 '
#3330
0"
#3335
b1001101 *
1"
#3336
b1001110 '
#3340
0"
#3345
b1001110 *
1"
#3346
b1001111 '
#3350
0"
#3355
b1001111 *
1"
#3356
b1010000 '
#3360
0"
#3365
b1010000 *
1"
#3366
b1010001 '
#3370
0"
#3375
b1010001 *
1"
#3376
b1010010 '
#3380
0"
#3385
b1010010 *
1"
#3386
b1010011 '
#3390
0"
#3395
b1010011 *
1"
#3396
b1010100 '
#3400
0"
#3405
b1010100 *
1"
#3406
b1010101 '
#3410
0"
#3415
b1010101 *
1"
#3416
b1010110 '
#3420
0"
#3425
b1010110 *
1"
#3426
b1010111 '
#3430
0"
#3435
b1010111 *
1"
#3436
b1011000 '
#3440
0"
#3445
b1011000 *
1"
#3446
b1011001 '
#3450
0"
#3455
b1011001 *
1"
#3456
b1011010 '
#3460
0"
#3465
b1011010 *
1"
#3466
b1011011 '
#3470
0"
#3475
b1011011 *
1"
#3476
b1011100 '
#3480
0"
#3485
b1011100 *
1"
#3486
b1011101 '
#3490
0"
#3495
b1011101 *
1"
#3496
b1011110 '
#3500
0"
#3505
b1011110 *
1"
#3506
b1011111 '
#3510
0"
#3515
b1011111 *
1"
#3516
b1100000 '
#3520
0"
#3525
b1100000 *
1"
#3526
b1100001 '
#3530
0"
#3535
b1100001 *
1"
#3536
b1100010 '
#3540
0"
#3545
b1100010 *
1"
#3546
b1100011 '
#3550
0"
#3555
b1100011 *
1"
#3556
b1100100 '
#3560
0"
#3565
b1100100 *
1"
#3566
b1100101 '
#3570
0"
#3575
b1100101 *
1"
#3576
b1100110 '
#3580
0"
#3585
b1100110 *
1"
#3586
b1100111 '
#3590
0"
#3595
b1100111 *
1"
#3596
b1101000 '
#3600
0"
#3605
b1101000 *
1"
#3606
b1101001 '
#3610
0"
#3615
b1101001 *
1"
#3616
b1101010 '
#3620
0"
#3625
b1101010 *
1"
#3626
b1101011 '
#3630
0"
#3635
b1101011 *
1"
#3636
b1101100 '
#3640
0"
#3645
b1101100 *
1"
#3646
b1101101 '
#3650
0"
#3655
b1101101 *
1"
#3656
b1101110 '
#3660
0"
#3665
b1101110 *
1"
#3666
b1101111 '
#3670
0"
#3675
b1101111 *
1"
#3676
b1110000 '
#3680
0"
#3685
b1110000 *
1"
#3686
b1110001 '
#3690
0"
#3695
b1110001 *
1"
#3696
b1110010 '
#3700
0"
#3705
b1110010 *
1"
#3706
b1110011 '
#3710
0"
#3715
b1110011 *
1"
#3716
b1110100 '
#3720
0"
#3725
b1110100 *
1"
#3726
b1110101 '
#3730
0"
#3735
b1110101 *
1"
#3736
b1110110 '
#3740
0"
#3745
b1110110 *
1"
#3746
b1110111 '
#3750
0"
#3755
b1110111 *
1"
#3756
b1111000 '
#3760
0"
#3765
b1111000 *
1"
#3766
b1111001 '
#3770
0"
#3775
b1111001 *
1"
#3776
b1111010 '
#3780
0"
#3785
b1111010 *
1"
#3786
b1111011 '
#3790
0"
#3795
b1111011 *
1"
#3796
b1111100 '
#3800
0"
#3805
b1111100 *
1"
#3806
b1111101 '
#3810
0"
#3815
b1111101 *
1"
#3816
b1111110 '
#3820
0"
#3825
b1111110 *
1"
#3826
b1111111 '
#3830
0"
#3835
b1111111 *
1"
#3836
b10000000 '
#3840
0"
#3845
b10000000 *
1"
#3846
b10000001 '
#3850
0"
#3855
b10000001 *
1"
#3856
b10000010 '
#3860
0"
#3865
b10000010 *
1"
#3866
b10000011 '
#3870
0"
#3875
b10000011 *
1"
#3876
b10000100 '
#3880
0"
#3885
b10000100 *
1"
#3886
b10000101 '
#3890
0"
#3895
b10000101 *
1"
#3896
b10000110 '
#3900
0"
#3905
b10000110 *
1"
#3906
b10000111 '
#3910
0"
#3915
b10000111 *
1"
#3916
b10001000 '
#3920
0"
#3925
b10001000 *
1"
#3926
b10001001 '
#3930
0"
#3935
b10001001 *
1"
#3936
b10001010 '
#3940
0"
#3945
b10001010 *
1"
#3946
b10001011 '
#3950
0"
#3955
b10001011 *
1"
#3956
b10001100 '
#3960
0"
#3965
b10001100 *
1"
#3966
b10001101 '
#3970
0"
#3975
b10001101 *
1"
#3976
b10001110 '
#3980
0"
#3985
b10001110 *
1"
#3986
b10001111 '
#3990
0"
#3995
b10001111 *
1"
#3996
b10010000 '
#4000
0"
#4005
b10010000 *
1"
#4006
b10010001 '
#4010
0"
#4015
b10010001 *
1"
#4016
b10010010 '
#4020
0"
#4025
b10010010 *
1"
#4026
b10010011 '
#4030
0"
#4035
b10010011 *
1"
#4036
b10010100 '
#4040
0"
#4045
b10010100 *
1"
#4046
b10010101 '
#4050
0"
#4055
b10010101 *
1"
#4056
b10010110 '
#4060
0"
#4065
b10010110 *
1"
#4066
b10010111 '
#4070
0"
#4075
b10010111 *
1"
#4076
b10011000 '
#4080
0"
#4085
b10011000 *
1"
#4086
b10011001 '
#4090
0"
#4095
b10011001 *
1"
#4096
b10011010 '
#4100
0"
#4105
b10011010 *
1"
#4106
b10011011 '
#4110
0"
#4115
b10011011 *
1"
#4116
b10011100 '
#4120
0"
#4125
b10011100 *
1"
#4126
b10011101 '
#4130
0"
#4135
b10011101 *
1"
#4136
b10011110 '
#4140
0"
#4145
b10011110 *
1"
#4146
b10011111 '
#4150
0"
#4155
b10011111 *
1"
#4156
b10100000 '
#4160
0"
#4165
b10100000 *
1"
#4166
b10100001 '
#4170
0"
#4175
b10100001 *
1"
#4176
b10100010 '
#4180
0"
#4185
b10100010 *
1"
#4186
b10100011 '
#4190
0"
#4195
b10100011 *
1"
#4196
b10100100 '
#4200
0"
#4205
b10100100 *
1"
#4206
b10100101 '
#4210
0"
#4215
b10100101 *
1"
#4216
b10100110 '
#4220
0"
#4225
b10100110 *
1"
#4226
b10100111 '
#4230
0"
#4235
b10100111 *
1"
#4236
b10101000 '
#4240
0"
#4245
b10101000 *
1"
#4246
b10101001 '
#4250
0"
#4255
b10101001 *
1"
#4256
b10101010 '
#4260
0"
#4265
b10101010 *
1"
#4266
b10101011 '
#4270
0"
#4275
b10101011 *
1"
#4276
b10101100 '
#4280
0"
#4285
b10101100 *
1"
#4286
b10101101 '
#4290
0"
#4295
b10101101 *
1"
#4296
b10101110 '
#4300
0"
#4305
b10101110 *
1"
#4306
b10101111 '
