seminars/week06/up_down_counter/up_down_counter.v
// synchronous up/down counter
module up_down_counter(
	input clk,				// clock, active in rising edge
	input up,				// counting enable up, higher priority then down counting
	input down,		   		// counting enable down
	output reg [7:0] data 	// output data
	);

    wire [7:0] value;

    assign value = up ? 1 : (down ? -1 : 0);

    always @(posedge clk)
        data <= data + value;

endmodule

seminars/week06/up_down_counter/up_down_counter_tb.v
`timescale 1ns/1ns

module up_down_counter_tb;
    parameter PERIOD = 10;

    integer i;

    reg         clk;
    reg         up;
    reg         down;
    reg         error;
    reg [7:0]   state;

    wire [7:0] out;

    up_down_counter t(.clk(clk), .up(up), .down(down), .data(out));

    initial begin
        clk     = 0;
        up      = 0;
        down    = 0;
        error   = 0;

        // There might be a problem in case of different solutions
        t.data = 0;
    end

    initial
        forever #(PERIOD / 2.0)
            clk = ~clk;

    task check;
    input [7:0] dir;
    begin
        state = out;

        for (i = 0; i < 10; i += 1)
        begin
            @(posedge clk) #1
            state += dir;

            if (state != out)
            begin
                error = 1;
                $display($time,, "Error: dir=%d, expected=%d, got=%d", dir, state, out);
            end
        end
    end
    endtask

    initial begin
        check(0);

        down = 1;
        check(-1);

        up   = 1;
        check(1);

        up   = 0;
        down = 0;
        check(0);

        up   = 1;
        check(1);

        if (error)
            $display("Tests failed!");
        else
            $display("Tests passed!");

        $finish;
    end

    initial begin
        $dumpfile("up_down_counter.vcd");
        $dumpvars(0, up_down_counter_tb);
    end
endmodule

seminars/week06/up_down_counter/up_down_counter.vcd
$date
	Wed Dec 20 21:29:43 2023
$end
$version
	Icarus Verilog
$end
$timescale
	1ns
$end
$scope module up_down_counter_tb $end
$var wire 8 ! out [7:0] $end
$var reg 1 " clk $end
$var reg 1 # down $end
$var reg 1 $ error $end
$var reg 8 % state [7:0] $end
$var reg 1 & up $end
$var integer 32 ' i [31:0] $end
$scope module t $end
$var wire 1 " clk $end
$var wire 1 # down $end
$var wire 1 & up $end
$var wire 8 ( value [7:0] $end
$var reg 8 ) data [7:0] $end
$upscope $end
$scope task check $end
$var reg 8 * dir [7:0] $end
$upscope $end
$upscope $end
$enddefinitions $end
#0
$dumpvars
b0 *
b0 )
b0 (
b0 '
0&
b0 %
0$
0#
0"
b0 !
$end
#5
1"
#6
b1 '
#10
0"
#15
1"
#16
b10 '
#20
0"
#25
1"
#26
b11 '
#30
0"
#35
1"
#36
b100 '
#40
0"
#45
1"
#46
b101 '
#50
0"
#55
1"
#56
b110 '
#60
0"
#65
1"
#66
b111 '
#70
0"
#75
1"
#76
b1000 '
#80
0"
#85
1"
#86
b1001 '
#90
0"
#95
1"
#96
b11111111 (
b11111111 *
1#
b0 '
#100
0"
#105
b11111111 !
b11111111 )
1"
#106
b1 '
b11111111 %
#110
0"
#115
b11111110 !
b11111110 )
1"
#116
b10 '
b11111110 %
#120
0"
#125
b11111101 !
b11111101 )
1"
#126
b11 '
b11111101 %
#130
0"
#135
b11111100 !
b11111100 )
1"
#136
b100 '
b11111100 %
#140
0"
#145
b11111011 !
b11111011 )
1"
#146
b101 '
b11111011 %
#150
0"
#155
b11111010 !
b11111010 )
1"
#156
b110 '
b11111010 %
#160
0"
#165
b11111001 !
b11111001 )
1"
#166
b111 '
b11111001 %
#170
0"
#175
b11111000 !
b11111000 )
1"
#176
b1000 '
b11111000 %
#180
0"
#185
b11110111 !
b11110111 )
1"
#186
b1001 '
b11110111 %
#190
0"
#195
b11110110 !
b11110110 )
1"
#196
b1 (
b1 *
1&
b0 '
b11110110 %
#200
0"
#205
b11110111 !
b11110111 )
1"
#206
b1 '
b11110111 %
#210
0"
#215
b11111000 !
b11111000 )
1"
#216
b10 '
b11111000 %
#220
0"
#225
b11111001 !
b11111001 )
1"
#226
b11 '
b11111001 %
#230
0"
#235
b11111010 !
b11111010 )
1"
#236
b100 '
b11111010 %
#240
0"
#245
b11111011 !
b11111011 )
1"
#246
b101 '
b11111011 %
#250
0"
#255
b11111100 !
b11111100 )
1"
#256
b110 '
b11111100 %
#260
0"
#265
b11111101 !
b11111101 )
1"
#266
b111 '
b11111101 %
#270
0"
#275
b11111110 !
b11111110 )
1"
#276
b1000 '
b11111110 %
#280
0"
#285
b11111111 !
b11111111 )
1"
#286
b1001 '
b11111111 %
#290
0"
#295
b0 !
b0 )
1"
#296
b0 (
b0 *
0#
0&
b0 '
b0 %
#300
0"
#305
1"
#306
b1 '
#310
0"
#315
1"
#316
b10 '
#320
0"
#325
1"
#326
b11 '
#330
0"
#335
1"
#336
b100 '
#340
0"
#345
1"
#346
b101 '
#350
0"
#355
1"
#356
b110 '
#360
0"
#365
1"
#366
b111 '
#370
0"
#375
1"
#376
b1000 '
#380
0"
#385
1"
#386
b1001 '
#390
0"
#395
1"
#396
b1 (
b1 *
1&
b0 '
#400
0"
#405
b1 !
b1 )
1"
#406
b1 '
b1 %
#410
0"
#415
b10 !
b10 )
1"
#416
b10 '
b10 %
#420
0"
#425
b11 !
b11 )
1"
#426
b11 '
b11 %
#430
0"
#435
b100 !
b100 )
1"
#436
b100 '
b100 %
#440
0"
#445
b101 !
b101 )
1"
#446
b101 '
b101 %
#450
0"
#455
b110 !
b110 )
1"
#456
b110 '
b110 %
#460
0"
#465
b111 !
b111 )
1"
#466
b111 '
b111 %
#470
0"
#475
b1000 !
b1000 )
1"
#476
b1000 '
b1000 %
#480
0"
#485
b1001 !
b1001 )
1"
#486
b1001 '
b1001 %
#490
0"
#495
b1010 !
b1010 )
1"
#496
b1010 '
b1010 %
