seminars/week06/find_rise/find_rise.v
module find_rise(input clk, input in, output reg out);
    reg prev;

    always @(posedge clk)
    begin
        prev    <= in;
        out     <= !prev && in;
    end
endmodule

seminars/week06/find_rise/find_rise_tb.v
`timescale 1ns/1ns

module find_rise_tb;
    parameter PERIOD = 10;

    reg clk;
    reg in;
    reg err;

    wire out;

    find_rise fr(.clk(clk), .in(in), .out(out));

    initial begin
        clk = 0;
        in  = 0;
        err = 0;

        fr.prev = 0;
    end

    initial begin
        forever #(PERIOD / 2.0)
            clk = ~clk;
    end

    initial begin
        @(posedge clk) #1
        err = err || (out != 0);

        @(posedge clk) #1
        err = err || (out != 0);

        @(negedge clk)
        in = 1;

        @(posedge clk) #1
        err = err || (out != 1);

        @(posedge clk) #1
        err = err || (out != 0);

        @(negedge clk)
        in = 0;

        @(posedge clk) #1
        err = err || (out != 0);

        @(negedge clk)
        in = 1;

        @(posedge clk) #1
        err = err || (out != 1);

        @(posedge clk) #1
        err = err || (out != 0);

        @(posedge clk) #1
        err = err || (out != 0);

        if (err)
            $display("Tests failed!");
        else
            $display("Tests passed!");

        $finish;
    end

    initial begin
        $dumpfile("find_rise.vcd");
        $dumpvars(0, find_rise_tb);
    end

endmodule

seminars/week06/find_rise/find_rise.vcd
$date
	Wed Dec 20 18:57:01 2023
$end
$version
	Icarus Verilog
$end
$timescale
	1ns
$end
$scope module find_rise_tb $end
$var wire 1 ! out $end
$var reg 1 " clk $end
$var reg 1 # err $end
$var reg 1 $ in $end
$scope module fr $end
$var wire 1 " clk $end
$var wire 1 $ in $end
$var reg 1 ! out $end
$var reg 1 % prev $end
$upscope $end
$upscope $end
$enddefinitions $end
#0
$dumpvars
0%
0$
0#
0"
x!
$end
#5
0!
1"
#10
0"
#15
1"
#20
1$
0"
#25
1!
1%
1"
#30
0"
#35
0!
1"
#40
0$
0"
#45
0%
1"
#50
1$
0"
#55
1!
1%
1"
#60
0"
#65
0!
1"
